LICENSE
MANIFEST.in
README.md
pyproject.toml
requirements.txt
setup.cfg
setup.py
django_rlists.egg-info/PKG-INFO
django_rlists.egg-info/SOURCES.txt
django_rlists.egg-info/dependency_links.txt
django_rlists.egg-info/requires.txt
django_rlists.egg-info/top_level.txt
docs/install.md
rlists/__init__.py
rlists/admin.py
rlists/apps.py
rlists/forms.py
rlists/models.py
rlists/tests.py
rlists/urls.py
rlists/views.py
rlists/fixtures/ratinglist.json
rlists/migrations/__init__.py
rlists/static/rlists/css/base.css
rlists/static/rlists/css/bootstrap-5.3.2.css
rlists/static/rlists/css/ratings.css
rlists/static/rlists/frl/fide_rating_lists.json
rlists/static/rlists/frl/fide_rating_lists.txt
rlists/static/rlists/frl/list.txt
rlists/static/rlists/img/favicon/favicon.ico
rlists/static/rlists/img/logo/chafua.jpg
rlists/static/rlists/js/base.js
rlists/static/rlists/js/bootstrap-5.3.2.js
rlists/static/rlists/js/bootstrap.bundle-5.3.2.js
rlists/static/rlists/js/jquery-3.6.1.js
rlists/static/rlists/js/ratings-processor.js
rlists/templates/rlists/base.html
rlists/templates/rlists/footer.html
rlists/templates/rlists/head.html
rlists/templates/rlists/navbar.html
rlists/templates/rlists/player_detail.html
rlists/templates/rlists/post.html
rlists/templates/rlists/rlist_detail.html
rlists/templates/rlists/success.html