Metadata-Version: 2.1
Name: django-rlists
Version: 0.2.0
Summary: A Django app for processing the FIDE rating lists of chess players.
Home-page: https://www.github.com/patrickwayodi/django-rlists
Author: Patrick Wayodi
Author-email: patrickwayodi@gmail.com
License: GNU General Public License
Classifier: Development Status :: 2 - Pre-Alpha
Classifier: Environment :: Web Environment
Classifier: Framework :: Django
Classifier: Framework :: Django :: 4.2
Classifier: Intended Audience :: Developers
Classifier: License :: OSI Approved :: GNU General Public License v3 or later (GPLv3+)
Classifier: Operating System :: OS Independent
Classifier: Programming Language :: Python
Classifier: Programming Language :: Python :: 3
Classifier: Programming Language :: Python :: 3 :: Only
Classifier: Programming Language :: Python :: 3.8
Classifier: Programming Language :: Python :: 3.9
Classifier: Programming Language :: Python :: 3.10
Classifier: Programming Language :: Python :: 3.11
Classifier: Programming Language :: Python :: 3.12
Classifier: Topic :: Internet :: WWW/HTTP
Classifier: Topic :: Internet :: WWW/HTTP :: Dynamic Content
Requires-Python: >=3.8
License-File: LICENSE
Requires-Dist: Django>=4.2
Requires-Dist: django-crispy-forms==2.1
Requires-Dist: matplotlib==3.8.2
Requires-Dist: Pillow==10.2.0
Requires-Dist: psycopg2==2.9.9
Requires-Dist: reportlab==4.0.9
